poisson_odds/__init__.py
poisson_odds/bookmaker_handicap.py
poisson_odds/bookmaker_moneyline.py
poisson_odds/bookmaker_total.py
poisson_odds/consts.py
poisson_odds/poisson.py
poisson_odds/probability.py
poisson_odds-0.1.3.dist-info/LICENSE
poisson_odds-0.1.3.dist-info/METADATA
poisson_odds-0.1.3.dist-info/WHEEL
poisson_odds-0.1.3.dist-info/top_level.txt
poisson_odds-0.1.3.dist-info/RECORD
